[{"id":1,"estado_id":1,"ciudad":"Maroa","capital":0},{"id":2,"estado_id":1,"ciudad":"Puerto Ayacucho","capital":1},{"id":3,"estado_id":1,"ciudad":"San Fernando de Atabapo","capital":0},{"id":4,"estado_id":2,"ciudad":"Anaco","capital":0},{"id":5,"estado_id":2,"ciudad":"Aragua de Barcelona","capital":0},{"id":6,"estado_id":2,"ciudad":"Barcelona","capital":1},{"id":7,"estado_id":2,"ciudad":"Boca de Uchire","capital":0},{"id":8,"estado_id":2,"ciudad":"Cantaura","capital":0},{"id":9,"estado_id":2,"ciudad":"Clarines","capital":0},{"id":10,"estado_id":2,"ciudad":"El Chaparro","capital":0},{"id":11,"estado_id":2,"ciudad":"El Pao Anzo\u00e1tegui","capital":0},{"id":12,"estado_id":2,"ciudad":"El Tigre","capital":0},{"id":13,"estado_id":2,"ciudad":"El Tigrito","capital":0},{"id":14,"estado_id":2,"ciudad":"Guanape","capital":0},{"id":15,"estado_id":2,"ciudad":"Guanta","capital":0},{"id":16,"estado_id":2,"ciudad":"Lecher\u00eda","capital":0},{"id":17,"estado_id":2,"ciudad":"Onoto","capital":0},{"id":18,"estado_id":2,"ciudad":"Pariagu\u00e1n","capital":0},{"id":19,"estado_id":2,"ciudad":"P\u00edritu","capital":0},{"id":20,"estado_id":2,"ciudad":"Puerto La Cruz","capital":0},{"id":21,"estado_id":2,"ciudad":"Puerto P\u00edritu","capital":0},{"id":22,"estado_id":2,"ciudad":"Sabana de Uchire","capital":0},{"id":23,"estado_id":2,"ciudad":"San Mateo Anzo\u00e1tegui","capital":0},{"id":24,"estado_id":2,"ciudad":"San Pablo Anzo\u00e1tegui","capital":0},{"id":25,"estado_id":2,"ciudad":"San Tom\u00e9","capital":0},{"id":26,"estado_id":2,"ciudad":"Santa Ana de Anzo\u00e1tegui","capital":0},{"id":27,"estado_id":2,"ciudad":"Santa Fe Anzo\u00e1tegui","capital":0},{"id":28,"estado_id":2,"ciudad":"Santa Rosa","capital":0},{"id":29,"estado_id":2,"ciudad":"Soledad","capital":0},{"id":30,"estado_id":2,"ciudad":"Urica","capital":0},{"id":31,"estado_id":2,"ciudad":"Valle de Guanape","capital":0},{"id":43,"estado_id":3,"ciudad":"Achaguas","capital":0},{"id":44,"estado_id":3,"ciudad":"Biruaca","capital":0},{"id":45,"estado_id":3,"ciudad":"Bruzual","capital":0},{"id":46,"estado_id":3,"ciudad":"El Amparo","capital":0},{"id":47,"estado_id":3,"ciudad":"El Nula","capital":0},{"id":48,"estado_id":3,"ciudad":"Elorza","capital":0},{"id":49,"estado_id":3,"ciudad":"Guasdualito","capital":0},{"id":50,"estado_id":3,"ciudad":"Mantecal","capital":0},{"id":51,"estado_id":3,"ciudad":"Puerto P\u00e1ez","capital":0},{"id":52,"estado_id":3,"ciudad":"San Fernando de Apure","capital":1},{"id":53,"estado_id":3,"ciudad":"San Juan de Payara","capital":0},{"id":54,"estado_id":4,"ciudad":"Barbacoas","capital":0},{"id":55,"estado_id":4,"ciudad":"Cagua","capital":0},{"id":56,"estado_id":4,"ciudad":"Camatagua","capital":0},{"id":58,"estado_id":4,"ciudad":"Choron\u00ed","capital":0},{"id":59,"estado_id":4,"ciudad":"Colonia Tovar","capital":0},{"id":60,"estado_id":4,"ciudad":"El Consejo","capital":0},{"id":61,"estado_id":4,"ciudad":"La Victoria","capital":0},{"id":62,"estado_id":4,"ciudad":"Las Tejer\u00edas","capital":0},{"id":63,"estado_id":4,"ciudad":"Magdaleno","capital":0},{"id":64,"estado_id":4,"ciudad":"Maracay","capital":1},{"id":65,"estado_id":4,"ciudad":"Ocumare de La Costa","capital":0},{"id":66,"estado_id":4,"ciudad":"Palo Negro","capital":0},{"id":67,"estado_id":4,"ciudad":"San Casimiro","capital":0},{"id":68,"estado_id":4,"ciudad":"San Mateo","capital":0},{"id":69,"estado_id":4,"ciudad":"San Sebasti\u00e1n","capital":0},{"id":70,"estado_id":4,"ciudad":"Santa Cruz de Aragua","capital":0},{"id":71,"estado_id":4,"ciudad":"Tocor\u00f3n","capital":0},{"id":72,"estado_id":4,"ciudad":"Turmero","capital":0},{"id":73,"estado_id":4,"ciudad":"Villa de Cura","capital":0},{"id":74,"estado_id":4,"ciudad":"Zuata","capital":0},{"id":75,"estado_id":5,"ciudad":"Barinas","capital":1},{"id":76,"estado_id":5,"ciudad":"Barinitas","capital":0},{"id":77,"estado_id":5,"ciudad":"Barrancas","capital":0},{"id":78,"estado_id":5,"ciudad":"Calderas","capital":0},{"id":79,"estado_id":5,"ciudad":"Capitanejo","capital":0},{"id":80,"estado_id":5,"ciudad":"Ciudad Bolivia","capital":0},{"id":81,"estado_id":5,"ciudad":"El Cant\u00f3n","capital":0},{"id":82,"estado_id":5,"ciudad":"Las Veguitas","capital":0},{"id":83,"estado_id":5,"ciudad":"Libertad de Barinas","capital":0},{"id":84,"estado_id":5,"ciudad":"Sabaneta","capital":0},{"id":85,"estado_id":5,"ciudad":"Santa B\u00e1rbara de Barinas","capital":0},{"id":86,"estado_id":5,"ciudad":"Socop\u00f3","capital":0},{"id":87,"estado_id":6,"ciudad":"Caicara del Orinoco","capital":0},{"id":88,"estado_id":6,"ciudad":"Canaima","capital":0},{"id":89,"estado_id":6,"ciudad":"Ciudad Bol\u00edvar","capital":1},{"id":90,"estado_id":6,"ciudad":"Ciudad Piar","capital":0},{"id":91,"estado_id":6,"ciudad":"El Callao","capital":0},{"id":92,"estado_id":6,"ciudad":"El Dorado","capital":0},{"id":93,"estado_id":6,"ciudad":"El Manteco","capital":0},{"id":94,"estado_id":6,"ciudad":"El Palmar","capital":0},{"id":95,"estado_id":6,"ciudad":"El Pao","capital":0},{"id":96,"estado_id":6,"ciudad":"Guasipati","capital":0},{"id":97,"estado_id":6,"ciudad":"Guri","capital":0},{"id":98,"estado_id":6,"ciudad":"La Paragua","capital":0},{"id":99,"estado_id":6,"ciudad":"Matanzas","capital":0},{"id":100,"estado_id":6,"ciudad":"Puerto Ordaz","capital":0},{"id":101,"estado_id":6,"ciudad":"San F\u00e9lix","capital":0},{"id":102,"estado_id":6,"ciudad":"Santa Elena de Uair\u00e9n","capital":0},{"id":103,"estado_id":6,"ciudad":"Tumeremo","capital":0},{"id":104,"estado_id":6,"ciudad":"Unare","capital":0},{"id":105,"estado_id":6,"ciudad":"Upata","capital":0},{"id":106,"estado_id":7,"ciudad":"Bejuma","capital":0},{"id":107,"estado_id":7,"ciudad":"Bel\u00e9n","capital":0},{"id":108,"estado_id":7,"ciudad":"Campo de Carabobo","capital":0},{"id":109,"estado_id":7,"ciudad":"Canoabo","capital":0},{"id":110,"estado_id":7,"ciudad":"Central Tacarigua","capital":0},{"id":111,"estado_id":7,"ciudad":"Chirgua","capital":0},{"id":112,"estado_id":7,"ciudad":"Ciudad Alianza","capital":0},{"id":113,"estado_id":7,"ciudad":"El Palito","capital":0},{"id":114,"estado_id":7,"ciudad":"Guacara","capital":0},{"id":115,"estado_id":7,"ciudad":"Guigue","capital":0},{"id":116,"estado_id":7,"ciudad":"Las Trincheras","capital":0},{"id":117,"estado_id":7,"ciudad":"Los Guayos","capital":0},{"id":118,"estado_id":7,"ciudad":"Mariara","capital":0},{"id":119,"estado_id":7,"ciudad":"Miranda","capital":0},{"id":120,"estado_id":7,"ciudad":"Montalb\u00e1n","capital":0},{"id":121,"estado_id":7,"ciudad":"Mor\u00f3n","capital":0},{"id":122,"estado_id":7,"ciudad":"Naguanagua","capital":0},{"id":123,"estado_id":7,"ciudad":"Puerto Cabello","capital":0},{"id":124,"estado_id":7,"ciudad":"San Joaqu\u00edn","capital":0},{"id":125,"estado_id":7,"ciudad":"Tocuyito","capital":0},{"id":126,"estado_id":7,"ciudad":"Urama","capital":0},{"id":127,"estado_id":7,"ciudad":"Valencia","capital":1},{"id":128,"estado_id":7,"ciudad":"Vigirimita","capital":0},{"id":129,"estado_id":8,"ciudad":"Aguirre","capital":0},{"id":130,"estado_id":8,"ciudad":"Apartaderos Cojedes","capital":0},{"id":131,"estado_id":8,"ciudad":"Arismendi","capital":0},{"id":132,"estado_id":8,"ciudad":"Camuriquito","capital":0},{"id":133,"estado_id":8,"ciudad":"El Ba\u00fal","capital":0},{"id":134,"estado_id":8,"ciudad":"El Lim\u00f3n","capital":0},{"id":135,"estado_id":8,"ciudad":"El Pao Cojedes","capital":0},{"id":136,"estado_id":8,"ciudad":"El Socorro","capital":0},{"id":137,"estado_id":8,"ciudad":"La Aguadita","capital":0},{"id":138,"estado_id":8,"ciudad":"Las Vegas","capital":0},{"id":139,"estado_id":8,"ciudad":"Libertad de Cojedes","capital":0},{"id":140,"estado_id":8,"ciudad":"Mapuey","capital":0},{"id":141,"estado_id":8,"ciudad":"Pi\u00f1edo","capital":0},{"id":142,"estado_id":8,"ciudad":"Samancito","capital":0},{"id":143,"estado_id":8,"ciudad":"San Carlos","capital":1},{"id":144,"estado_id":8,"ciudad":"Sucre","capital":0},{"id":145,"estado_id":8,"ciudad":"Tinaco","capital":0},{"id":146,"estado_id":8,"ciudad":"Tinaquillo","capital":0},{"id":147,"estado_id":8,"ciudad":"Vallecito","capital":0},{"id":148,"estado_id":9,"ciudad":"Tucupita","capital":1},{"id":149,"estado_id":24,"ciudad":"Caracas","capital":1},{"id":150,"estado_id":24,"ciudad":"El Junquito","capital":0},{"id":151,"estado_id":10,"ciudad":"Ad\u00edcora","capital":0},{"id":152,"estado_id":10,"ciudad":"Boca de Aroa","capital":0},{"id":153,"estado_id":10,"ciudad":"Cabure","capital":0},{"id":154,"estado_id":10,"ciudad":"Capadare","capital":0},{"id":155,"estado_id":10,"ciudad":"Capat\u00e1rida","capital":0},{"id":156,"estado_id":10,"ciudad":"Chichiriviche","capital":0},{"id":157,"estado_id":10,"ciudad":"Churuguara","capital":0},{"id":158,"estado_id":10,"ciudad":"Coro","capital":1},{"id":159,"estado_id":10,"ciudad":"Cumarebo","capital":0},{"id":160,"estado_id":10,"ciudad":"Dabajuro","capital":0},{"id":161,"estado_id":10,"ciudad":"Judibana","capital":0},{"id":162,"estado_id":10,"ciudad":"La Cruz de Taratara","capital":0},{"id":163,"estado_id":10,"ciudad":"La Vela de Coro","capital":0},{"id":164,"estado_id":10,"ciudad":"Los Taques","capital":0},{"id":165,"estado_id":10,"ciudad":"Maparari","capital":0},{"id":166,"estado_id":10,"ciudad":"Mene de Mauroa","capital":0},{"id":167,"estado_id":10,"ciudad":"Mirimire","capital":0},{"id":168,"estado_id":10,"ciudad":"Pedregal","capital":0},{"id":169,"estado_id":10,"ciudad":"P\u00edritu Falc\u00f3n","capital":0},{"id":170,"estado_id":10,"ciudad":"Pueblo Nuevo Falc\u00f3n","capital":0},{"id":171,"estado_id":10,"ciudad":"Puerto Cumarebo","capital":0},{"id":172,"estado_id":10,"ciudad":"Punta Card\u00f3n","capital":0},{"id":173,"estado_id":10,"ciudad":"Punto Fijo","capital":0},{"id":174,"estado_id":10,"ciudad":"San Juan de Los Cayos","capital":0},{"id":175,"estado_id":10,"ciudad":"San Luis","capital":0},{"id":176,"estado_id":10,"ciudad":"Santa Ana Falc\u00f3n","capital":0},{"id":177,"estado_id":10,"ciudad":"Santa Cruz De Bucaral","capital":0},{"id":178,"estado_id":10,"ciudad":"Tocopero","capital":0},{"id":179,"estado_id":10,"ciudad":"Tocuyo de La Costa","capital":0},{"id":180,"estado_id":10,"ciudad":"Tucacas","capital":0},{"id":181,"estado_id":10,"ciudad":"Yaracal","capital":0},{"id":182,"estado_id":11,"ciudad":"Altagracia de Orituco","capital":0},{"id":183,"estado_id":11,"ciudad":"Cabruta","capital":0},{"id":184,"estado_id":11,"ciudad":"Calabozo","capital":0},{"id":185,"estado_id":11,"ciudad":"Camagu\u00e1n","capital":0},{"id":196,"estado_id":11,"ciudad":"Chaguaramas Gu\u00e1rico","capital":0},{"id":197,"estado_id":11,"ciudad":"El Socorro","capital":0},{"id":198,"estado_id":11,"ciudad":"El Sombrero","capital":0},{"id":199,"estado_id":11,"ciudad":"Las Mercedes de Los Llanos","capital":0},{"id":200,"estado_id":11,"ciudad":"Lezama","capital":0},{"id":201,"estado_id":11,"ciudad":"Onoto","capital":0},{"id":202,"estado_id":11,"ciudad":"Ort\u00edz","capital":0},{"id":203,"estado_id":11,"ciudad":"San Jos\u00e9 de Guaribe","capital":0},{"id":204,"estado_id":11,"ciudad":"San Juan de Los Morros","capital":1},{"id":205,"estado_id":11,"ciudad":"San Rafael de Laya","capital":0},{"id":206,"estado_id":11,"ciudad":"Santa Mar\u00eda de Ipire","capital":0},{"id":207,"estado_id":11,"ciudad":"Tucupido","capital":0},{"id":208,"estado_id":11,"ciudad":"Valle de La Pascua","capital":0},{"id":209,"estado_id":11,"ciudad":"Zaraza","capital":0},{"id":210,"estado_id":12,"ciudad":"Aguada Grande","capital":0},{"id":211,"estado_id":12,"ciudad":"Atarigua","capital":0},{"id":212,"estado_id":12,"ciudad":"Barquisimeto","capital":1},{"id":213,"estado_id":12,"ciudad":"Bobare","capital":0},{"id":214,"estado_id":12,"ciudad":"Cabudare","capital":0},{"id":215,"estado_id":12,"ciudad":"Carora","capital":0},{"id":216,"estado_id":12,"ciudad":"Cubiro","capital":0},{"id":217,"estado_id":12,"ciudad":"Cuj\u00ed","capital":0},{"id":218,"estado_id":12,"ciudad":"Duaca","capital":0},{"id":219,"estado_id":12,"ciudad":"El Manzano","capital":0},{"id":220,"estado_id":12,"ciudad":"El Tocuyo","capital":0},{"id":221,"estado_id":12,"ciudad":"Guar\u00edco","capital":0},{"id":222,"estado_id":12,"ciudad":"Humocaro Alto","capital":0},{"id":223,"estado_id":12,"ciudad":"Humocaro Bajo","capital":0},{"id":224,"estado_id":12,"ciudad":"La Miel","capital":0},{"id":225,"estado_id":12,"ciudad":"Moroturo","capital":0},{"id":226,"estado_id":12,"ciudad":"Qu\u00edbor","capital":0},{"id":227,"estado_id":12,"ciudad":"R\u00edo Claro","capital":0},{"id":228,"estado_id":12,"ciudad":"Sanare","capital":0},{"id":229,"estado_id":12,"ciudad":"Santa In\u00e9s","capital":0},{"id":230,"estado_id":12,"ciudad":"Sarare","capital":0},{"id":231,"estado_id":12,"ciudad":"Siquisique","capital":0},{"id":232,"estado_id":12,"ciudad":"Tintorero","capital":0},{"id":233,"estado_id":13,"ciudad":"Apartaderos M\u00e9rida","capital":0},{"id":234,"estado_id":13,"ciudad":"Arapuey","capital":0},{"id":235,"estado_id":13,"ciudad":"Bailadores","capital":0},{"id":236,"estado_id":13,"ciudad":"Caja Seca","capital":0},{"id":237,"estado_id":13,"ciudad":"Canagu\u00e1","capital":0},{"id":238,"estado_id":13,"ciudad":"Chachopo","capital":0},{"id":239,"estado_id":13,"ciudad":"Chiguara","capital":0},{"id":240,"estado_id":13,"ciudad":"Ejido","capital":0},{"id":241,"estado_id":13,"ciudad":"El Vig\u00eda","capital":0},{"id":242,"estado_id":13,"ciudad":"La Azulita","capital":0},{"id":243,"estado_id":13,"ciudad":"La Playa","capital":0},{"id":244,"estado_id":13,"ciudad":"Lagunillas M\u00e9rida","capital":0},{"id":245,"estado_id":13,"ciudad":"M\u00e9rida","capital":1},{"id":246,"estado_id":13,"ciudad":"Mesa de Bol\u00edvar","capital":0},{"id":247,"estado_id":13,"ciudad":"Mucuch\u00edes","capital":0},{"id":248,"estado_id":13,"ciudad":"Mucujepe","capital":0},{"id":249,"estado_id":13,"ciudad":"Mucuruba","capital":0},{"id":250,"estado_id":13,"ciudad":"Nueva Bolivia","capital":0},{"id":251,"estado_id":13,"ciudad":"Palmarito","capital":0},{"id":252,"estado_id":13,"ciudad":"Pueblo Llano","capital":0},{"id":253,"estado_id":13,"ciudad":"Santa Cruz de Mora","capital":0},{"id":254,"estado_id":13,"ciudad":"Santa Elena de Arenales","capital":0},{"id":255,"estado_id":13,"ciudad":"Santo Domingo","capital":0},{"id":256,"estado_id":13,"ciudad":"Tab\u00e1y","capital":0},{"id":257,"estado_id":13,"ciudad":"Timotes","capital":0},{"id":258,"estado_id":13,"ciudad":"Torondoy","capital":0},{"id":259,"estado_id":13,"ciudad":"Tovar","capital":0},{"id":260,"estado_id":13,"ciudad":"Tucani","capital":0},{"id":261,"estado_id":13,"ciudad":"Zea","capital":0},{"id":262,"estado_id":14,"ciudad":"Araguita","capital":0},{"id":263,"estado_id":14,"ciudad":"Carrizal","capital":0},{"id":264,"estado_id":14,"ciudad":"Caucagua","capital":0},{"id":265,"estado_id":14,"ciudad":"Chaguaramas Miranda","capital":0},{"id":266,"estado_id":14,"ciudad":"Charallave","capital":0},{"id":267,"estado_id":14,"ciudad":"Chirimena","capital":0},{"id":268,"estado_id":14,"ciudad":"Chuspa","capital":0},{"id":269,"estado_id":14,"ciudad":"C\u00faa","capital":0},{"id":270,"estado_id":14,"ciudad":"Cupira","capital":0},{"id":271,"estado_id":14,"ciudad":"Curiepe","capital":0},{"id":272,"estado_id":14,"ciudad":"El Guapo","capital":0},{"id":273,"estado_id":14,"ciudad":"El Jarillo","capital":0},{"id":274,"estado_id":14,"ciudad":"Filas de Mariche","capital":0},{"id":275,"estado_id":14,"ciudad":"Guarenas","capital":0},{"id":276,"estado_id":14,"ciudad":"Guatire","capital":0},{"id":277,"estado_id":14,"ciudad":"Higuerote","capital":0},{"id":278,"estado_id":14,"ciudad":"Los Anaucos","capital":0},{"id":279,"estado_id":14,"ciudad":"Los Teques","capital":1},{"id":280,"estado_id":14,"ciudad":"Ocumare del Tuy","capital":0},{"id":281,"estado_id":14,"ciudad":"Panaquire","capital":0},{"id":282,"estado_id":14,"ciudad":"Paracotos","capital":0},{"id":283,"estado_id":14,"ciudad":"R\u00edo Chico","capital":0},{"id":284,"estado_id":14,"ciudad":"San Antonio de Los Altos","capital":0},{"id":285,"estado_id":14,"ciudad":"San Diego de Los Altos","capital":0},{"id":286,"estado_id":14,"ciudad":"San Fernando del Guapo","capital":0},{"id":287,"estado_id":14,"ciudad":"San Francisco de Yare","capital":0},{"id":288,"estado_id":14,"ciudad":"San Jos\u00e9 de Los Altos","capital":0},{"id":289,"estado_id":14,"ciudad":"San Jos\u00e9 de R\u00edo Chico","capital":0},{"id":290,"estado_id":14,"ciudad":"San Pedro de Los Altos","capital":0},{"id":291,"estado_id":14,"ciudad":"Santa Luc\u00eda","capital":0},{"id":292,"estado_id":14,"ciudad":"Santa Teresa","capital":0},{"id":293,"estado_id":14,"ciudad":"Tacarigua de La Laguna","capital":0},{"id":294,"estado_id":14,"ciudad":"Tacarigua de Mamporal","capital":0},{"id":295,"estado_id":14,"ciudad":"T\u00e1cata","capital":0},{"id":296,"estado_id":14,"ciudad":"Turumo","capital":0},{"id":297,"estado_id":15,"ciudad":"Aguasay","capital":0},{"id":298,"estado_id":15,"ciudad":"Aragua de Matur\u00edn","capital":0},{"id":299,"estado_id":15,"ciudad":"Barrancas del Orinoco","capital":0},{"id":300,"estado_id":15,"ciudad":"Caicara de Matur\u00edn","capital":0},{"id":301,"estado_id":15,"ciudad":"Caripe","capital":0},{"id":302,"estado_id":15,"ciudad":"Caripito","capital":0},{"id":303,"estado_id":15,"ciudad":"Chaguaramal","capital":0},{"id":305,"estado_id":15,"ciudad":"Chaguaramas Monagas","capital":0},{"id":307,"estado_id":15,"ciudad":"El Furrial","capital":0},{"id":308,"estado_id":15,"ciudad":"El Tejero","capital":0},{"id":309,"estado_id":15,"ciudad":"Jusep\u00edn","capital":0},{"id":310,"estado_id":15,"ciudad":"La Toscana","capital":0},{"id":311,"estado_id":15,"ciudad":"Matur\u00edn","capital":1},{"id":312,"estado_id":15,"ciudad":"Miraflores","capital":0},{"id":313,"estado_id":15,"ciudad":"Punta de Mata","capital":0},{"id":314,"estado_id":15,"ciudad":"Quiriquire","capital":0},{"id":315,"estado_id":15,"ciudad":"San Antonio de Matur\u00edn","capital":0},{"id":316,"estado_id":15,"ciudad":"San Vicente Monagas","capital":0},{"id":317,"estado_id":15,"ciudad":"Santa B\u00e1rbara","capital":0},{"id":318,"estado_id":15,"ciudad":"Temblador","capital":0},{"id":319,"estado_id":15,"ciudad":"Teresen","capital":0},{"id":320,"estado_id":15,"ciudad":"Uracoa","capital":0},{"id":321,"estado_id":16,"ciudad":"Altagracia","capital":0},{"id":322,"estado_id":16,"ciudad":"Boca de Pozo","capital":0},{"id":323,"estado_id":16,"ciudad":"Boca de R\u00edo","capital":0},{"id":324,"estado_id":16,"ciudad":"El Espinal","capital":0},{"id":325,"estado_id":16,"ciudad":"El Valle del Esp\u00edritu Santo","capital":0},{"id":326,"estado_id":16,"ciudad":"El Yaque","capital":0},{"id":327,"estado_id":16,"ciudad":"Juangriego","capital":0},{"id":328,"estado_id":16,"ciudad":"La Asunci\u00f3n","capital":1},{"id":329,"estado_id":16,"ciudad":"La Guardia","capital":0},{"id":330,"estado_id":16,"ciudad":"Pampatar","capital":0},{"id":331,"estado_id":16,"ciudad":"Porlamar","capital":0},{"id":332,"estado_id":16,"ciudad":"Puerto Ferm\u00edn","capital":0},{"id":333,"estado_id":16,"ciudad":"Punta de Piedras","capital":0},{"id":334,"estado_id":16,"ciudad":"San Francisco de Macanao","capital":0},{"id":335,"estado_id":16,"ciudad":"San Juan Bautista","capital":0},{"id":336,"estado_id":16,"ciudad":"San Pedro de Coche","capital":0},{"id":337,"estado_id":16,"ciudad":"Santa Ana de Nueva Esparta","capital":0},{"id":338,"estado_id":16,"ciudad":"Villa Rosa","capital":0},{"id":339,"estado_id":17,"ciudad":"Acarigua","capital":0},{"id":340,"estado_id":17,"ciudad":"Agua Blanca","capital":0},{"id":341,"estado_id":17,"ciudad":"Araure","capital":0},{"id":342,"estado_id":17,"ciudad":"Biscucuy","capital":0},{"id":343,"estado_id":17,"ciudad":"Boconoito","capital":0},{"id":344,"estado_id":17,"ciudad":"Campo El\u00edas","capital":0},{"id":345,"estado_id":17,"ciudad":"Chabasqu\u00e9n","capital":0},{"id":346,"estado_id":17,"ciudad":"Guanare","capital":1},{"id":347,"estado_id":17,"ciudad":"Guanarito","capital":0},{"id":348,"estado_id":17,"ciudad":"La Aparici\u00f3n","capital":0},{"id":349,"estado_id":17,"ciudad":"La Misi\u00f3n","capital":0},{"id":350,"estado_id":17,"ciudad":"Mesa de Cavacas","capital":0},{"id":351,"estado_id":17,"ciudad":"Ospino","capital":0},{"id":352,"estado_id":17,"ciudad":"Papel\u00f3n","capital":0},{"id":353,"estado_id":17,"ciudad":"Payara","capital":0},{"id":354,"estado_id":17,"ciudad":"Pimpinela","capital":0},{"id":355,"estado_id":17,"ciudad":"P\u00edritu de Portuguesa","capital":0},{"id":356,"estado_id":17,"ciudad":"San Rafael de Onoto","capital":0},{"id":357,"estado_id":17,"ciudad":"Santa Rosal\u00eda","capital":0},{"id":358,"estado_id":17,"ciudad":"Tur\u00e9n","capital":0},{"id":359,"estado_id":18,"ciudad":"Altos de Sucre","capital":0},{"id":360,"estado_id":18,"ciudad":"Araya","capital":0},{"id":361,"estado_id":18,"ciudad":"Cariaco","capital":0},{"id":362,"estado_id":18,"ciudad":"Car\u00fapano","capital":0},{"id":363,"estado_id":18,"ciudad":"Casanay","capital":0},{"id":364,"estado_id":18,"ciudad":"Cuman\u00e1","capital":1},{"id":365,"estado_id":18,"ciudad":"Cumanacoa","capital":0},{"id":366,"estado_id":18,"ciudad":"El Morro Puerto Santo","capital":0},{"id":367,"estado_id":18,"ciudad":"El Pilar","capital":0},{"id":368,"estado_id":18,"ciudad":"El Poblado","capital":0},{"id":369,"estado_id":18,"ciudad":"Guaca","capital":0},{"id":370,"estado_id":18,"ciudad":"Guiria","capital":0},{"id":371,"estado_id":18,"ciudad":"Irapa","capital":0},{"id":372,"estado_id":18,"ciudad":"Manicuare","capital":0},{"id":373,"estado_id":18,"ciudad":"Mariguitar","capital":0},{"id":374,"estado_id":18,"ciudad":"R\u00edo Caribe","capital":0},{"id":375,"estado_id":18,"ciudad":"San Antonio del Golfo","capital":0},{"id":376,"estado_id":18,"ciudad":"San Jos\u00e9 de Aerocuar","capital":0},{"id":377,"estado_id":18,"ciudad":"San Vicente de Sucre","capital":0},{"id":378,"estado_id":18,"ciudad":"Santa Fe de Sucre","capital":0},{"id":379,"estado_id":18,"ciudad":"Tunapuy","capital":0},{"id":380,"estado_id":18,"ciudad":"Yaguaraparo","capital":0},{"id":381,"estado_id":18,"ciudad":"Yoco","capital":0},{"id":382,"estado_id":19,"ciudad":"Abejales","capital":0},{"id":383,"estado_id":19,"ciudad":"Borota","capital":0},{"id":384,"estado_id":19,"ciudad":"Bramon","capital":0},{"id":385,"estado_id":19,"ciudad":"Capacho","capital":0},{"id":386,"estado_id":19,"ciudad":"Col\u00f3n","capital":0},{"id":387,"estado_id":19,"ciudad":"Coloncito","capital":0},{"id":388,"estado_id":19,"ciudad":"Cordero","capital":0},{"id":389,"estado_id":19,"ciudad":"El Cobre","capital":0},{"id":390,"estado_id":19,"ciudad":"El Pinal","capital":0},{"id":391,"estado_id":19,"ciudad":"Independencia","capital":0},{"id":392,"estado_id":19,"ciudad":"La Fr\u00eda","capital":0},{"id":393,"estado_id":19,"ciudad":"La Grita","capital":0},{"id":394,"estado_id":19,"ciudad":"La Pedrera","capital":0},{"id":395,"estado_id":19,"ciudad":"La Tendida","capital":0},{"id":396,"estado_id":19,"ciudad":"Las Delicias","capital":0},{"id":397,"estado_id":19,"ciudad":"Las Hern\u00e1ndez","capital":0},{"id":398,"estado_id":19,"ciudad":"Lobatera","capital":0},{"id":399,"estado_id":19,"ciudad":"Michelena","capital":0},{"id":400,"estado_id":19,"ciudad":"Palmira","capital":0},{"id":401,"estado_id":19,"ciudad":"Pregonero","capital":0},{"id":402,"estado_id":19,"ciudad":"Queniquea","capital":0},{"id":403,"estado_id":19,"ciudad":"Rubio","capital":0},{"id":404,"estado_id":19,"ciudad":"San Antonio del Tachira","capital":0},{"id":405,"estado_id":19,"ciudad":"San Cristobal","capital":1},{"id":406,"estado_id":19,"ciudad":"San Jos\u00e9 de Bol\u00edvar","capital":0},{"id":407,"estado_id":19,"ciudad":"San Josecito","capital":0},{"id":408,"estado_id":19,"ciudad":"San Pedro del R\u00edo","capital":0},{"id":409,"estado_id":19,"ciudad":"Santa Ana T\u00e1chira","capital":0},{"id":410,"estado_id":19,"ciudad":"Seboruco","capital":0},{"id":411,"estado_id":19,"ciudad":"T\u00e1riba","capital":0},{"id":412,"estado_id":19,"ciudad":"Umuquena","capital":0},{"id":413,"estado_id":19,"ciudad":"Ure\u00f1a","capital":0},{"id":414,"estado_id":20,"ciudad":"Batatal","capital":0},{"id":415,"estado_id":20,"ciudad":"Betijoque","capital":0},{"id":416,"estado_id":20,"ciudad":"Bocon\u00f3","capital":0},{"id":417,"estado_id":20,"ciudad":"Carache","capital":0},{"id":418,"estado_id":20,"ciudad":"Chejende","capital":0},{"id":419,"estado_id":20,"ciudad":"Cuicas","capital":0},{"id":420,"estado_id":20,"ciudad":"El Dividive","capital":0},{"id":421,"estado_id":20,"ciudad":"El Jaguito","capital":0},{"id":422,"estado_id":20,"ciudad":"Escuque","capital":0},{"id":423,"estado_id":20,"ciudad":"Isnot\u00fa","capital":0},{"id":424,"estado_id":20,"ciudad":"Jaj\u00f3","capital":0},{"id":425,"estado_id":20,"ciudad":"La Ceiba","capital":0},{"id":426,"estado_id":20,"ciudad":"La Concepci\u00f3n de Trujllo","capital":0},{"id":427,"estado_id":20,"ciudad":"La Mesa de Esnujaque","capital":0},{"id":428,"estado_id":20,"ciudad":"La Puerta","capital":0},{"id":429,"estado_id":20,"ciudad":"La Quebrada","capital":0},{"id":430,"estado_id":20,"ciudad":"Mendoza Fr\u00eda","capital":0},{"id":431,"estado_id":20,"ciudad":"Meseta de Chimpire","capital":0},{"id":432,"estado_id":20,"ciudad":"Monay","capital":0},{"id":433,"estado_id":20,"ciudad":"Motat\u00e1n","capital":0},{"id":434,"estado_id":20,"ciudad":"Pamp\u00e1n","capital":0},{"id":435,"estado_id":20,"ciudad":"Pampanito","capital":0},{"id":436,"estado_id":20,"ciudad":"Sabana de Mendoza","capital":0},{"id":437,"estado_id":20,"ciudad":"San L\u00e1zaro","capital":0},{"id":438,"estado_id":20,"ciudad":"Santa Ana de Trujillo","capital":0},{"id":439,"estado_id":20,"ciudad":"Tost\u00f3s","capital":0},{"id":440,"estado_id":20,"ciudad":"Trujillo","capital":1},{"id":441,"estado_id":20,"ciudad":"Valera","capital":0},{"id":442,"estado_id":21,"ciudad":"Carayaca","capital":0},{"id":443,"estado_id":21,"ciudad":"Litoral","capital":0},{"id":444,"estado_id":25,"ciudad":"Archipi\u00e9lago Los Roques","capital":0},{"id":445,"estado_id":22,"ciudad":"Aroa","capital":0},{"id":446,"estado_id":22,"ciudad":"Boraure","capital":0},{"id":447,"estado_id":22,"ciudad":"Campo El\u00edas de Yaracuy","capital":0},{"id":448,"estado_id":22,"ciudad":"Chivacoa","capital":0},{"id":449,"estado_id":22,"ciudad":"Cocorote","capital":0},{"id":450,"estado_id":22,"ciudad":"Farriar","capital":0},{"id":451,"estado_id":22,"ciudad":"Guama","capital":0},{"id":452,"estado_id":22,"ciudad":"Mar\u00edn","capital":0},{"id":453,"estado_id":22,"ciudad":"Nirgua","capital":0},{"id":454,"estado_id":22,"ciudad":"Sabana de Parra","capital":0},{"id":455,"estado_id":22,"ciudad":"Salom","capital":0},{"id":456,"estado_id":22,"ciudad":"San Felipe","capital":1},{"id":457,"estado_id":22,"ciudad":"San Pablo de Yaracuy","capital":0},{"id":458,"estado_id":22,"ciudad":"Urachiche","capital":0},{"id":459,"estado_id":22,"ciudad":"Yaritagua","capital":0},{"id":460,"estado_id":22,"ciudad":"Yumare","capital":0},{"id":461,"estado_id":23,"ciudad":"Bachaquero","capital":0},{"id":462,"estado_id":23,"ciudad":"Bobures","capital":0},{"id":463,"estado_id":23,"ciudad":"Cabimas","capital":0},{"id":464,"estado_id":23,"ciudad":"Campo Concepci\u00f3n","capital":0},{"id":465,"estado_id":23,"ciudad":"Campo Mara","capital":0},{"id":466,"estado_id":23,"ciudad":"Campo Rojo","capital":0},{"id":467,"estado_id":23,"ciudad":"Carrasquero","capital":0},{"id":468,"estado_id":23,"ciudad":"Casigua","capital":0},{"id":469,"estado_id":23,"ciudad":"Chiquinquir\u00e1","capital":0},{"id":470,"estado_id":23,"ciudad":"Ciudad Ojeda","capital":0},{"id":471,"estado_id":23,"ciudad":"El Batey","capital":0},{"id":472,"estado_id":23,"ciudad":"El Carmelo","capital":0},{"id":473,"estado_id":23,"ciudad":"El Chivo","capital":0},{"id":474,"estado_id":23,"ciudad":"El Guayabo","capital":0},{"id":475,"estado_id":23,"ciudad":"El Mene","capital":0},{"id":476,"estado_id":23,"ciudad":"El Venado","capital":0},{"id":477,"estado_id":23,"ciudad":"Encontrados","capital":0},{"id":478,"estado_id":23,"ciudad":"Gibraltar","capital":0},{"id":479,"estado_id":23,"ciudad":"Isla de Toas","capital":0},{"id":480,"estado_id":23,"ciudad":"La Concepci\u00f3n del Zulia","capital":0},{"id":481,"estado_id":23,"ciudad":"La Paz","capital":0},{"id":482,"estado_id":23,"ciudad":"La Sierrita","capital":0},{"id":483,"estado_id":23,"ciudad":"Lagunillas del Zulia","capital":0},{"id":484,"estado_id":23,"ciudad":"Las Piedras de Perij\u00e1","capital":0},{"id":485,"estado_id":23,"ciudad":"Los Cortijos","capital":0},{"id":486,"estado_id":23,"ciudad":"Machiques","capital":0},{"id":487,"estado_id":23,"ciudad":"Maracaibo","capital":1},{"id":488,"estado_id":23,"ciudad":"Mene Grande","capital":0},{"id":489,"estado_id":23,"ciudad":"Palmarejo","capital":0},{"id":490,"estado_id":23,"ciudad":"Paraguaipoa","capital":0},{"id":491,"estado_id":23,"ciudad":"Potrerito","capital":0},{"id":492,"estado_id":23,"ciudad":"Pueblo Nuevo del Zulia","capital":0},{"id":493,"estado_id":23,"ciudad":"Puertos de Altagracia","capital":0},{"id":494,"estado_id":23,"ciudad":"Punta Gorda","capital":0},{"id":495,"estado_id":23,"ciudad":"Sabaneta de Palma","capital":0},{"id":496,"estado_id":23,"ciudad":"San Francisco","capital":0},{"id":497,"estado_id":23,"ciudad":"San Jos\u00e9 de Perij\u00e1","capital":0},{"id":498,"estado_id":23,"ciudad":"San Rafael del Moj\u00e1n","capital":0},{"id":499,"estado_id":23,"ciudad":"San Timoteo","capital":0},{"id":500,"estado_id":23,"ciudad":"Santa B\u00e1rbara Del Zulia","capital":0},{"id":501,"estado_id":23,"ciudad":"Santa Cruz de Mara","capital":0},{"id":502,"estado_id":23,"ciudad":"Santa Cruz del Zulia","capital":0},{"id":503,"estado_id":23,"ciudad":"Santa Rita","capital":0},{"id":504,"estado_id":23,"ciudad":"Sinamaica","capital":0},{"id":505,"estado_id":23,"ciudad":"Tamare","capital":0},{"id":506,"estado_id":23,"ciudad":"T\u00eda Juana","capital":0},{"id":507,"estado_id":23,"ciudad":"Villa del Rosario","capital":0},{"id":508,"estado_id":21,"ciudad":"La Guaira","capital":1},{"id":509,"estado_id":21,"ciudad":"Catia La Mar","capital":0},{"id":510,"estado_id":21,"ciudad":"Macuto","capital":0},{"id":511,"estado_id":21,"ciudad":"Naiguat\u00e1","capital":0},{"id":512,"estado_id":25,"ciudad":"Archipi\u00e9lago Los Monjes","capital":0},{"id":513,"estado_id":25,"ciudad":"Isla La Tortuga y Cayos adyacentes","capital":0},{"id":514,"estado_id":25,"ciudad":"Isla La Sola","capital":0},{"id":515,"estado_id":25,"ciudad":"Islas Los Testigos","capital":0},{"id":516,"estado_id":25,"ciudad":"Islas Los Frailes","capital":0},{"id":517,"estado_id":25,"ciudad":"Isla La Orchila","capital":0},{"id":518,"estado_id":25,"ciudad":"Archipi\u00e9lago Las Aves","capital":0},{"id":519,"estado_id":25,"ciudad":"Isla de Aves","capital":0},{"id":520,"estado_id":25,"ciudad":"Isla La Blanquilla","capital":0},{"id":521,"estado_id":25,"ciudad":"Isla de Patos","capital":0},{"id":522,"estado_id":25,"ciudad":"Islas Los Hermanos","capital":0}]